mem_edit/LICENSE.md
mem_edit/README.md
mem_edit/__init__.py
mem_edit/abstract.py
mem_edit/linux.py
mem_edit/utils.py
mem_edit/windows.py
mem_edit-0.8.dist-info/METADATA
mem_edit-0.8.dist-info/WHEEL
mem_edit-0.8.dist-info/licenses/LICENSE.md
mem_edit-0.8.dist-info/RECORD
