Metadata-Version: 2.3
Name: mem_edit
Version: 0.8
Summary: Multi-platform library for memory editing
Author-email: Jan Petykiewicz <jan@mpxd.net>
License: GNU Affero General Public License
License-File: LICENSE.md
Keywords: ReadProcessMemory,WriteProcessMemory,cheat,debug,edit,editing,mem,memory,multiplatform,proc,ptrace,scan,scanner,search,trainer
Classifier: Development Status :: 5 - Production/Stable
Classifier: Environment :: Other Environment
Classifier: Intended Audience :: Developers
Classifier: License :: OSI Approved :: GNU Affero General Public License v3
Classifier: Operating System :: Microsoft :: Windows
Classifier: Operating System :: POSIX :: Linux
Classifier: Programming Language :: Python :: 3
Classifier: Topic :: Games/Entertainment
Classifier: Topic :: Software Development
Classifier: Topic :: Software Development :: Debuggers
Classifier: Topic :: Software Development :: Testing
Classifier: Topic :: System
Classifier: Topic :: Utilities
Requires-Python: >=3.11
